pyuson/__init__.py
pyuson/__main__.py
pyuson/_types.py
pyuson/assets/config_default.toml
pyuson/assets/icon.png
pyuson/assets/icon.svg
pyuson/config/__init__.py
pyuson/config/_base.py
pyuson/config/_config.py
pyuson/config/_types.py
pyuson/config/models.py
pyuson/data/__init__.py
pyuson/data/_data.py
pyuson/gui/__init__.py
pyuson/gui/_base.py
pyuson/gui/_core.py
pyuson/gui/_workers.py
pyuson/gui/protocols/__init__.py
pyuson/gui/protocols/_wbatch.py
pyuson/gui/protocols/_wbuttons.py
pyuson/gui/protocols/_wconfiguration.py
pyuson/gui/protocols/_wfiles.py
pyuson/gui/protocols/_worker.py
pyuson/gui/protocols/_wplots.py
pyuson/gui/widgets/__init__.py
pyuson/gui/widgets/_batch_processing_tab.py
pyuson/gui/widgets/_configuration_tab.py
pyuson/gui/widgets/_drop_list.py
pyuson/gui/widgets/_file_browser.py
pyuson/gui/widgets/_files_tab.py
pyuson/gui/widgets/_graphs.py
pyuson/gui/widgets/_main_buttons.py
pyuson/gui/widgets/_param_content.py
pyuson/gui/widgets/_popup_progress_bar.py
pyuson/gui/widgets/_text_logger.py
pyuson/processors/__init__.py
pyuson/processors/_base.py
pyuson/processors/_echo.py
pyuson/processors/_types.py
pyuson/py.typed
pyuson/sp.py
pyuson/utils.py
pyuson-0.7.5.dist-info/WHEEL
pyuson-0.7.5.dist-info/entry_points.txt
pyuson-0.7.5.dist-info/METADATA
pyuson-0.7.5.dist-info/RECORD
