Metadata-Version: 2.3
Name: pyuson
Version: 0.7.5
Summary: Ultra-sound attenuation and phase-shift computation during high magnetic field.
Author: Guillaume Le Goc
Author-email: Guillaume Le Goc <guillaume.le-goc@lncmi.cnrs.fr>
Requires-Dist: fftekwfm>=0.3.0.1
Requires-Dist: matplotlib>=3.10.3
Requires-Dist: nexusformat>=2.0.0
Requires-Dist: numpy>=2.2.0
Requires-Dist: pydantic>=2.11.9
Requires-Dist: pyqt6>=6.9.1
Requires-Dist: pyqtgraph>=0.13.7
Requires-Dist: rich>=14.1.0
Requires-Dist: scipy>=1.15.3
Requires-Dist: tomlkit>=0.13.3
Requires-Dist: mkdocs>=1.6.1 ; extra == 'docs'
Requires-Dist: mkdocs-git-revision-date-localized-plugin>=1.4.7 ; extra == 'docs'
Requires-Dist: mkdocs-jupyter>=0.25.1 ; extra == 'docs'
Requires-Dist: mkdocs-material>=9.6.16 ; extra == 'docs'
Requires-Dist: mkdocstrings>=0.30.0 ; extra == 'docs'
Requires-Dist: mkdocstrings-python>=1.16.12 ; extra == 'docs'
Requires-Python: >=3.12
Provides-Extra: docs
